[{"id":"38949545277","type":"CreateEvent","createdAt":"2024-06-03T14:48:29Z","payload":{"repoName":"cspray/annotated-container","repoUrl":"https://github.com/cspray/annotated-container","refType":"branch","branch":"task/tools"}},{"id":"38926381731","type":"PushEvent","createdAt":"2024-06-03T00:21:34Z","payload":{"repoName":"cspray/annotated-container","repoUrl":"https://github.com/cspray/annotated-container","branch":"release-2.x","branchUrl":"https://github.com/cspray/annotated-container/tree/release-2.x","head":"de89bb5","headUrl":"https://github.com/cspray/annotated-container/commit/de89bb54613ed0b2d6a02b3f4af057da177b4382"}},{"id":"38925806365","type":"CreateEvent","createdAt":"2024-06-02T23:16:05Z","payload":{"repoName":"cspray/annotated-container","repoUrl":"https://github.com/cspray/annotated-container","refType":"branch","branch":"feature/inject-array-services"}},{"id":"38889836918","type":"CreateEvent","createdAt":"2024-05-31T15:12:14Z","payload":{"repoName":"labrador-kennel/async-event","repoUrl":"https://github.com/labrador-kennel/async-event","refType":"tag"}},{"id":"38889829282","type":"PushEvent","createdAt":"2024-05-31T15:11:59Z","payload":{"repoName":"labrador-kennel/async-event","repoUrl":"https://github.com/labrador-kennel/async-event","branch":"main","branchUrl":"https://github.com/labrador-kennel/async-event/tree/main","head":"f7a625c","headUrl":"https://github.com/labrador-kennel/async-event/commit/f7a625c3be9812d2cb9a58d2b4e08f6b81d69207"}},{"id":"38889779241","type":"PushEvent","createdAt":"2024-05-31T15:10:23Z","payload":{"repoName":"labrador-kennel/async-event","repoUrl":"https://github.com/labrador-kennel/async-event","branch":"task/allow-string-enum-events","branchUrl":"https://github.com/labrador-kennel/async-event/tree/task/allow-string-enum-events","head":"a767cc6","headUrl":"https://github.com/labrador-kennel/async-event/commit/a767cc6aed60ef9ea3c6dfb3ba94e46707a4ba45"}},{"id":"38889622041","type":"CreateEvent","createdAt":"2024-05-31T15:05:40Z","payload":{"repoName":"labrador-kennel/async-event","repoUrl":"https://github.com/labrador-kennel/async-event","refType":"branch","branch":"task/allow-string-enum-events"}},{"id":"38870217274","type":"CreateEvent","createdAt":"2024-05-31T02:38:25Z","payload":{"repoName":"labrador-kennel/async-unit","repoUrl":"https://github.com/labrador-kennel/async-unit","refType":"branch","branch":"task/amp-v3-support"}},{"id":"38863534254","type":"CreateEvent","createdAt":"2024-05-30T20:02:08Z","payload":{"repoName":"labrador-kennel/async-event-autowire","repoUrl":"https://github.com/labrador-kennel/async-event-autowire","refType":"tag"}},{"id":"38863528738","type":"PushEvent","createdAt":"2024-05-30T20:01:56Z","payload":{"repoName":"labrador-kennel/async-event-autowire","repoUrl":"https://github.com/labrador-kennel/async-event-autowire","branch":"main","branchUrl":"https://github.com/labrador-kennel/async-event-autowire/tree/main","head":"2cbb9d9","headUrl":"https://github.com/labrador-kennel/async-event-autowire/commit/2cbb9d9222e463a546099d84bfbd91c9529503a2"}},{"id":"38863470669","type":"CreateEvent","createdAt":"2024-05-30T19:59:43Z","payload":{"repoName":"labrador-kennel/async-event-autowire","repoUrl":"https://github.com/labrador-kennel/async-event-autowire","refType":"branch","branch":"feature/async-event-v4"}},{"id":"38863003788","type":"CreateEvent","createdAt":"2024-05-30T19:40:38Z","payload":{"repoName":"labrador-kennel/async-event","repoUrl":"https://github.com/labrador-kennel/async-event","refType":"tag"}},{"id":"38862983496","type":"PushEvent","createdAt":"2024-05-30T19:39:49Z","payload":{"repoName":"labrador-kennel/async-event","repoUrl":"https://github.com/labrador-kennel/async-event","branch":"main","branchUrl":"https://github.com/labrador-kennel/async-event/tree/main","head":"932791a","headUrl":"https://github.com/labrador-kennel/async-event/commit/932791a3d49990e0d56addf696dcc56d00f569a3"}},{"id":"38862964214","type":"PushEvent","createdAt":"2024-05-30T19:39:03Z","payload":{"repoName":"labrador-kennel/async-event","repoUrl":"https://github.com/labrador-kennel/async-event","branch":"feature/version-4","branchUrl":"https://github.com/labrador-kennel/async-event/tree/feature/version-4","head":"71fee35","headUrl":"https://github.com/labrador-kennel/async-event/commit/71fee35f0f3593e9d7845c98b16323c95d84c70b"}}]