[{"id":"38987625572","type":"WatchEvent","createdAt":"2024-06-04T14:33:26Z","payload":{"repoName":"LadybirdWebBrowser/ladybird","repoUrl":"https://github.com/LadybirdWebBrowser/ladybird","action":"started"}},{"id":"38984399217","type":"PushEvent","createdAt":"2024-06-04T13:14:18Z","payload":{"repoName":"cspray/annotated-container","repoUrl":"https://github.com/cspray/annotated-container","branch":"release-3.x","branchUrl":"https://github.com/cspray/annotated-container/tree/release-3.x","head":"2a26d1b","headUrl":"https://github.com/cspray/annotated-container/commit/2a26d1b5c8708338647da260c17544fc747e64f0"}},{"id":"38964464907","type":"PushEvent","createdAt":"2024-06-04T00:27:29Z","payload":{"repoName":"cspray/annotated-container","repoUrl":"https://github.com/cspray/annotated-container","branch":"release-2.x","branchUrl":"https://github.com/cspray/annotated-container/tree/release-2.x","head":"31189e1","headUrl":"https://github.com/cspray/annotated-container/commit/31189e1c631e51159fc1abf867c708e8717b3d2d"}},{"id":"38964427898","type":"PushEvent","createdAt":"2024-06-04T00:25:03Z","payload":{"repoName":"cspray/annotated-container","repoUrl":"https://github.com/cspray/annotated-container","branch":"task/trigger-deprecations","branchUrl":"https://github.com/cspray/annotated-container/tree/task/trigger-deprecations","head":"f74ecfe","headUrl":"https://github.com/cspray/annotated-container/commit/f74ecfe273a81ff15cc7e7b375eff370ffa069f9"}},{"id":"38964391176","type":"CreateEvent","createdAt":"2024-06-04T00:22:40Z","payload":{"repoName":"cspray/annotated-container","repoUrl":"https://github.com/cspray/annotated-container","refType":"branch","branch":"task/trigger-deprecations"}},{"id":"38963881562","type":"PushEvent","createdAt":"2024-06-03T23:50:11Z","payload":{"repoName":"cspray/annotated-container","repoUrl":"https://github.com/cspray/annotated-container","branch":"release-2.x","branchUrl":"https://github.com/cspray/annotated-container/tree/release-2.x","head":"9c00ced","headUrl":"https://github.com/cspray/annotated-container/commit/9c00ced6ea950aa503eaec6ea8009d8db4c03159"}},{"id":"38963853099","type":"CreateEvent","createdAt":"2024-06-03T23:48:19Z","payload":{"repoName":"cspray/annotated-container","repoUrl":"https://github.com/cspray/annotated-container","refType":"branch","branch":"task/upgrade-phpunit-11"}},{"id":"38962851038","type":"PushEvent","createdAt":"2024-06-03T22:44:28Z","payload":{"repoName":"cspray/annotated-container","repoUrl":"https://github.com/cspray/annotated-container","branch":"release-2.x","branchUrl":"https://github.com/cspray/annotated-container/tree/release-2.x","head":"2a4db3b","headUrl":"https://github.com/cspray/annotated-container/commit/2a4db3b417a5e0db776ab2b87cb511e11c962e33"}},{"id":"38962836107","type":"CreateEvent","createdAt":"2024-06-03T22:43:31Z","payload":{"repoName":"cspray/annotated-container","repoUrl":"https://github.com/cspray/annotated-container","refType":"branch","branch":"task/add-justfile"}},{"id":"38962617052","type":"PushEvent","createdAt":"2024-06-03T22:31:07Z","payload":{"repoName":"cspray/minicli","repoUrl":"https://github.com/cspray/minicli","branch":"main","branchUrl":"https://github.com/cspray/minicli/tree/main","head":"1675c06","headUrl":"https://github.com/cspray/minicli/commit/1675c0609205c106bb7c2353888dec361808d92e"}},{"id":"38962161992","type":"CreateEvent","createdAt":"2024-06-03T22:08:02Z","payload":{"repoName":"cspray/annotated-container-adr","repoUrl":"https://github.com/cspray/annotated-container-adr","refType":"tag"}},{"id":"38962157544","type":"PushEvent","createdAt":"2024-06-03T22:07:48Z","payload":{"repoName":"cspray/annotated-container-adr","repoUrl":"https://github.com/cspray/annotated-container-adr","branch":"main","branchUrl":"https://github.com/cspray/annotated-container-adr/tree/main","head":"3195f41","headUrl":"https://github.com/cspray/annotated-container-adr/commit/3195f41234e9a8fbf8a4f47984717167d45a39da"}},{"id":"38962148412","type":"CreateEvent","createdAt":"2024-06-03T22:07:21Z","payload":{"repoName":"cspray/annotated-container-adr","repoUrl":"https://github.com/cspray/annotated-container-adr","refType":"branch","branch":"task/arch-decision-1.4"}},{"id":"38962119873","type":"CreateEvent","createdAt":"2024-06-03T22:05:54Z","payload":{"repoName":"cspray/architectural-decision","repoUrl":"https://github.com/cspray/architectural-decision","refType":"tag"}}]