[{"id":"33794276978","type":"PushEvent","createdAt":"2023-12-01T14:24:16Z","payload":{"repoName":"labrador-kennel/framework","repoUrl":"https://github.com/labrador-kennel/framework","branch":"main","branchUrl":"https://github.com/labrador-kennel/framework/tree/main","head":"36b3a50","headUrl":"https://github.com/labrador-kennel/framework/commit/36b3a502b1dea380bc34dae4397c5697f264033b"}},{"id":"33794242906","type":"CreateEvent","createdAt":"2023-12-01T14:23:19Z","payload":{"repoName":"labrador-kennel/framework","repoUrl":"https://github.com/labrador-kennel/framework","refType":"branch","branch":"task/fix-middleware-stack"}}]